basicRISCV/RTL/gpio_reg_ip.v
module GPIO_register_ip (
    input en,
    input clk,
    input wr,
    input [7:0] addr_offset,
    input [31:0] data_in,
    output reg [31:0] data_out);

reg [31:0] data;
reg [31:0] dir;
reg [31:0] gpio_in = 32'h0;
reg [31:0] gpio_out;

initial
    begin
      $display("Hello, World");
    //   $monitor("Time=%0t | data_in=%b, data_out=%b, clk=%b, en=%b, wr=%b", $time, data_in, data_out, clk, en, wr);
    end


always @ (posedge clk) begin
    if (en) begin
        if (wr) begin
            case (addr_offset)
                8'h00: data <= data_in; // Write to GPIO Data Register
                8'h04: dir <= data_in; // Write to GPIO Direction Register
                default: ; // Do nothing for other addresses
            endcase
        end else begin
            case (addr_offset)
                8'h00: data_out <= data; // Read from GPIO Data Register
                8'h04: data_out <= dir; // Read from GPIO Direction Register
                8'h08: data_out <= (data & dir)|(gpio_in & ~dir); // Read from GPIO Input Register (masked by direction)
                default: ; // Default read value
            endcase
        end
     gpio_out <= data & dir;
    end
end
endmodule

basicRISCV/RTL/gpio_reg_ip_tb.v
`timescale 1ns/1ps

module tb_gpio_reg_ip;
  reg en;
  reg clk;
  reg wr;
  reg [7:0] addr_offset;
  reg [31:0] data_in;
  wire [31:0] data_out;

  GPIO_register_ip dut (
    .en(en),
    .clk(clk),
    .wr(wr),
    .addr_offset(addr_offset),
    .data_in(data_in),
    .data_out(data_out)
  );

  always #5 clk = ~clk;

  initial begin
    $dumpfile("gpio_reg_ip.vcd");
    $dumpvars(0, tb_gpio_reg_ip);

    en = 1;
    clk = 0;
    wr = 0;

    addr_offset = 0;

    #10;
    addr_offset = 32'h4; 

    #10;
    addr_offset = 32'h8; 

    #10;
    wr = 1;
    addr_offset = 32'h0; // Set address offset to 0x0 (data register)
    data_in = 32'hA5A5A5A5;
    
    #10;
    wr = 1;
    addr_offset = 32'h4; // Set address offset to 0x4 (direction register)
    data_in = 32'hFFFFFFF0; // Set all pins as output except the last 4

    #10
    wr = 0;
    addr_offset = 32'h0; // Set address offset to 0x0 (data register)

    #10
    addr_offset = 32'h4; // Set address offset to 0x4 (direction register)

    #10
    addr_offset = 32'h8; // Set address offset to 0x8 (read register)


    #20;
    $finish;
  end

endmodule

basicRISCV/RTL/gpio_reg_ip.vcd
$date
	Sun Feb  8 23:14:01 2026
$end
$version
	Icarus Verilog
$end
$timescale
	1ps
$end
$scope module tb_gpio_reg_ip $end
$var wire 32 ! data_out [31:0] $end
$var reg 8 " addr_offset [7:0] $end
$var reg 1 # clk $end
$var reg 32 $ data_in [31:0] $end
$var reg 1 % en $end
$var reg 1 & wr $end
$scope module dut $end
$var wire 8 ' addr_offset [7:0] $end
$var wire 1 # clk $end
$var wire 32 ( data_in [31:0] $end
$var wire 1 % en $end
$var wire 1 & wr $end
$var reg 32 ) data [31:0] $end
$var reg 32 * data_out [31:0] $end
$var reg 32 + dir [31:0] $end
$var reg 32 , gpio_in [31:0] $end
$var reg 32 - gpio_out [31:0] $end
$upscope $end
$upscope $end
$enddefinitions $end
$comment Show the parameter values. $end
$dumpall
$end
#0
$dumpvars
bx -
b0 ,
bx +
bx *
bx )
bx (
b0 '
0&
1%
bx $
0#
b0 "
bx !
$end
#5000
1#
#10000
0#
b100 "
b100 '
#15000
1#
#20000
0#
b1000 "
b1000 '
#25000
1#
#30000
0#
b10100101101001011010010110100101 $
b10100101101001011010010110100101 (
b0 "
b0 '
1&
#35000
b10100101101001011010010110100101 )
1#
#40000
0#
b11111111111111111111111111110000 $
b11111111111111111111111111110000 (
b100 "
b100 '
#45000
bx0x00x0xx0x00x0xx0x00x0xx0x00x0x -
b11111111111111111111111111110000 +
1#
#50000
0#
b0 "
b0 '
0&
#55000
b10100101101001011010010110100000 -
b10100101101001011010010110100101 !
b10100101101001011010010110100101 *
1#
#60000
0#
b100 "
b100 '
#65000
b11111111111111111111111111110000 !
b11111111111111111111111111110000 *
1#
#70000
0#
b1000 "
b1000 '
#75000
b10100101101001011010010110100000 !
b10100101101001011010010110100000 *
1#
