basicRISCV/RTL/i2c_master_standard_.v
module I2C_master_standard (
    input         clk,
    input         rst_n,
    input         wr_en,
    input         r_en,
    input  [7:0]  addr_offset,
    input  [31:0] data_in,
    output reg [31:0] data_out,
    output reg    scl,
    inout         sda
);

    // ---------------------------------
    // Registers
    // ---------------------------------
    reg        start_enable;
    reg [7:0]  clk_div;
    reg [6:0]  slave_addr;
    reg [7:0]  data_to_send;
    reg [7:0]  data_received;
    reg [1:0]  status;
    reg        mode;          // 0 = TX, 1 = RX

    reg [7:0]  clk_count;
    reg [4:0]  bit_index;

    // SDA open-drain control
    reg sda_drive_low;
    assign sda = sda_drive_low ? 1'b0 : 1'bz;

    // ---------------------------------
    // Register interface
    // ---------------------------------
    always @(posedge clk or negedge rst_n) begin
        if (!rst_n) begin
            start_enable <= 1'b0;
            clk_div      <= 8'd1;
            slave_addr   <= 7'd0;
            data_to_send <= 8'd0;
            data_received <= 8'd0;
            status       <= 2'd0;
            mode         <= 1'b0;
            data_out     <= 32'd0;
        end else begin
            if (wr_en) begin
                case (addr_offset)
                    8'h00: start_enable <= |data_in;
                    8'h04: clk_div      <= data_in[7:0];
                    8'h08: slave_addr   <= data_in[6:0];
                    8'h0C: data_to_send <= data_in[7:0];
                    8'h18: mode         <= data_in[0];
                    default: ;
                endcase
            end
        end
    end

    always @(*) begin
        if (r_en) begin
            case (addr_offset)
                8'h00: data_out = start_enable;
                8'h04: data_out = clk_div;
                8'h08: data_out = {25'd0, slave_addr};
                8'h10: data_out = {24'd0, data_received};
                8'h14: data_out = status;
                8'h18: data_out = {31'd0, mode};
                default: data_out = 32'd0;
            endcase
        end else begin
            data_out = 32'd0;
        end
        
    end

    // ---------------------------------
    // SCL clock divider
    // ---------------------------------
    always @(posedge clk or negedge rst_n) begin
        if (!rst_n) begin
            clk_count <= 8'd0;
            scl       <= 1'b1;
        end else if (!start_enable) begin
            scl <= 1'b1; // Idle state of SCL is high
        end else if (clk_div <= 1) begin
            scl <= clk;
        end else begin
            if (clk_count == (clk_div >> 1) - 1) begin
                clk_count <= 8'd0;
                scl <= ~scl;
            end else begin
                clk_count <= clk_count + 1'b1;
            end
        end
    end

    // ---------------------------------
    // I2C transmit / receive (simplified)
    // ---------------------------------
    always @(posedge scl or negedge rst_n) begin
        if (!rst_n) begin
            bit_index     <= 5'd0;
            sda_drive_low <= 1'b0;
            data_received <= 8'd0;
        end else begin

            if (bit_index == 0) begin
                status <= 2'b01; // BUSY
            end
            // Address + R/W bit
            if (bit_index < 7) begin
                sda_drive_low <= ~slave_addr[6 - bit_index];
                bit_index <= bit_index + 1;
            end else if (bit_index == 7) begin
                sda_drive_low <= ~mode; // R/W bit
                bit_index <= bit_index + 1;
            end

            // ACK bit
            else if (bit_index == 8) begin
                sda_drive_low <= 1'b0; // release SDA
                bit_index <= bit_index + 1;
            end else if (bit_index == 9) begin
                if (sda == 1'b0) begin
                    status[1:0] <= 2'b10;
                    bit_index <= bit_index + 1;
                end else status[1:0] <= 2'b11;
            end

            // Data phase
            else if (bit_index < 18 && mode == 1'b0) begin
                sda_drive_low <= ~data_to_send[17 - bit_index];
                bit_index <= bit_index + 1;
            end else if (bit_index < 18 && mode == 1'b1) begin
                data_received[15 - bit_index] <= sda;
                bit_index <= bit_index + 1;
            end

            // Done
            else begin
                sda_drive_low <= 1'b0;
                bit_index <= 5'd0;
                status <= 2'b00; // done
                start_enable <= 1'b0; // auto-clear start
            end
        end
    end

endmodule

basicRISCV/RTL/i2c_master_standard_tb.v
`timescale 1ns/1ps

module tb_I2C_master_standard;

    // ----------------------------------
    // TB signals
    // ----------------------------------
    reg         clk;
    reg         rst_n;
    reg         wr_en;
    reg         r_en;
    reg [7:0]   addr_offset;
    reg [31:0]  data_in;
    wire [31:0] data_out;
    wire        scl;
    wire        sda;

    // Slave-side SDA drive (open drain)
    reg sda_slave_drive;

    // Open-drain behavior
    assign sda = (sda_slave_drive) ? 1'b0 : 1'bz;

    // ----------------------------------
    // DUT
    // ----------------------------------
    I2C_master_standard dut (
        .clk(clk),
        .rst_n(rst_n),
        .wr_en(wr_en),
        .r_en(r_en),
        .addr_offset(addr_offset),
        .data_in(data_in),
        .data_out(data_out),
        .scl(scl),
        .sda(sda)
    );

    // ----------------------------------
    // Clock generation (50 MHz)
    // ----------------------------------
    initial clk = 0;
    always #10 clk = ~clk;

    // ----------------------------------
    // Register write task
    // ----------------------------------
    task reg_write(input [7:0] addr, input [31:0] data);
        begin
            @(posedge clk);
            wr_en     <= 1'b1;
            r_en      <= 1'b0;
            addr_offset<= addr;
            data_in    <= data;
            // @(posedge clk);
            // wr          <= 1'b0;
            // addr_offset<= 8'h00;
            // data_in    <= 32'h0;
        end
    endtask

    // ----------------------------------
    // Register read task
    // ----------------------------------
    task reg_read(input [7:0] addr);
        begin
            @(posedge clk);
            wr_en     <= 1'b0;
            r_en      <= 1'b1;
            addr_offset<= addr;
            @(posedge clk);
            $display("[%0t] READ  addr 0x%02h -> 0x%08h",
                     $time, addr, data_out);
        end
    endtask

    // ----------------------------------
    // Very simple I2C slave ACK model
    // ----------------------------------
    // Pull SDA low during ACK bit (bit_index == 8)
    always @(posedge scl) begin
        if (dut.bit_index == 8)
            sda_slave_drive <= 1'b1; // ACK
        else
            sda_slave_drive <= 1'b0;
    end

    // ----------------------------------
    // Test sequence
    // ----------------------------------
    initial begin
        $display("====================================");
        $display("   I2C MASTER STANDARD TB START");
        $display("====================================");
        $dumpfile("i2c_master_standard.vcd");
        $dumpvars(0, tb_I2C_master_standard);

        // Init
        wr_en = 0;
        r_en = 0;
        addr_offset = 0;
        data_in = 0;
        sda_slave_drive = 0;
        rst_n = 0;

        // Reset
        #100;
        rst_n = 1;

        // -----------------------------
        // Program registers
        // -----------------------------
        wr_en = 1;
        reg_write(8'h04, 32'd2);   // clk_div
        reg_write(8'h08, 32'h55);   // slave address
        reg_write(8'h0C, 32'hA6);   // data to send
        reg_write(8'h18, 32'd0);    // mode = transmit
        reg_write(8'h00, 32'd1);    // start_enable

        #40;
        wr_en = 0; // Stop writing registers
        // Let I2C activity run
        #3000;

        // -----------------------------
        // Readback registers
        // -----------------------------
        r_en = 1;
        reg_read(8'h00);
        reg_read(8'h04);
        reg_read(8'h08);
        reg_read(8'h0C);
        reg_read(8'h10);
        reg_read(8'h14);
        reg_read(8'h18);

        #500;
        $display("====================================");
        $display("   I2C MASTER STANDARD TB END");
        $display("====================================");
        $stop;
    end

endmodule

basicRISCV/RTL/i2c_master_standard.vcd
$date
	Wed Feb 11 00:09:56 2026
$end
$version
	Icarus Verilog
$end
$timescale
	1ps
$end
$scope module tb_I2C_master_standard $end
$var wire 1 ! sda $end
$var wire 1 " scl $end
$var wire 32 # data_out [31:0] $end
$var reg 8 $ addr_offset [7:0] $end
$var reg 1 % clk $end
$var reg 32 & data_in [31:0] $end
$var reg 1 ' r_en $end
$var reg 1 ( rst_n $end
$var reg 1 ) sda_slave_drive $end
$var reg 1 * wr_en $end
$scope module dut $end
$var wire 8 + addr_offset [7:0] $end
$var wire 1 % clk $end
$var wire 32 , data_in [31:0] $end
$var wire 1 ' r_en $end
$var wire 1 ( rst_n $end
$var wire 1 ! sda $end
$var wire 1 * wr_en $end
$var reg 5 - bit_index [4:0] $end
$var reg 8 . clk_count [7:0] $end
$var reg 8 / clk_div [7:0] $end
$var reg 32 0 data_out [31:0] $end
$var reg 8 1 data_received [7:0] $end
$var reg 8 2 data_to_send [7:0] $end
$var reg 1 3 mode $end
$var reg 1 " scl $end
$var reg 1 4 sda_drive_low $end
$var reg 7 5 slave_addr [6:0] $end
$var reg 1 6 start_enable $end
$var reg 2 7 status [1:0] $end
$upscope $end
$scope task reg_read $end
$var reg 8 8 addr [7:0] $end
$upscope $end
$scope task reg_write $end
$var reg 8 9 addr [7:0] $end
$var reg 32 : data [31:0] $end
$upscope $end
$upscope $end
$enddefinitions $end
$comment Show the parameter values. $end
$dumpall
$end
#0
$dumpvars
bx :
bx 9
bx 8
b0 7
06
b0 5
04
03
b0 2
b0 1
b0 0
b1 /
b0 .
b0 -
b0 ,
b0 +
0*
0)
0(
0'
b0 &
0%
b0 $
b0 #
1"
z!
$end
#10000
1%
#20000
0%
#30000
1%
#40000
0%
#50000
1%
#60000
0%
#70000
1%
#80000
0%
#90000
1%
#100000
0%
b10 :
b100 9
1*
1(
#110000
b10 &
b10 ,
b100 $
b100 +
b1010101 :
b1000 9
1%
#120000
0%
#130000
b10 /
b1010101 &
b1010101 ,
b1000 $
b1000 +
b10100110 :
b1100 9
1%
#140000
0%
#150000
b1010101 5
b10100110 &
b10100110 ,
b1100 $
b1100 +
b0 :
b11000 9
1%
#160000
0%
#170000
b10100110 2
b0 &
b0 ,
b11000 $
b11000 +
b1 :
b0 9
1%
#180000
0%
#190000
b1 &
b1 ,
b0 $
b0 +
1%
#200000
0%
#210000
16
1%
#220000
0%
#230000
0"
1%
0*
#240000
0%
#250000
b1 -
b1 7
1"
1%
#260000
0%
#270000
0"
1%
#280000
0%
#290000
0!
b10 -
14
1"
1%
#300000
0%
#310000
0"
1%
#320000
0%
#330000
z!
b11 -
04
1"
1%
#340000
0%
#350000
0"
1%
#360000
0%
#370000
0!
b100 -
14
1"
1%
#380000
0%
#390000
0"
1%
#400000
0%
#410000
z!
b101 -
04
1"
1%
#420000
0%
#430000
0"
1%
#440000
0%
#450000
0!
b110 -
14
1"
1%
#460000
0%
#470000
0"
1%
#480000
0%
#490000
z!
b111 -
04
1"
1%
#500000
0%
#510000
0"
1%
#520000
0%
#530000
0!
b1000 -
14
1"
1%
#540000
0%
#550000
0"
1%
#560000
0%
#570000
b1001 -
04
1)
1"
1%
#580000
0%
#590000
0"
1%
#600000
0%
#610000
z!
b1010 -
b10 7
0)
1"
1%
#620000
0%
#630000
0"
1%
#640000
0%
#650000
b1011 -
1"
1%
#660000
0%
#670000
0"
1%
#680000
0%
#690000
0!
b1100 -
14
1"
1%
#700000
0%
#710000
0"
1%
#720000
0%
#730000
z!
b1101 -
04
1"
1%
#740000
0%
#750000
0"
1%
#760000
0%
#770000
0!
b1110 -
14
1"
1%
#780000
0%
#790000
0"
1%
#800000
0%
#810000
b1111 -
1"
1%
#820000
0%
#830000
0"
1%
#840000
0%
#850000
z!
b10000 -
04
1"
1%
#860000
0%
#870000
0"
1%
#880000
0%
#890000
b10001 -
1"
1%
#900000
0%
#910000
0"
1%
#920000
0%
#930000
0!
b10010 -
14
1"
1%
#940000
0%
#950000
0"
1%
#960000
0%
#970000
z!
06
b0 7
b0 -
04
1"
1%
